poetryupvers/__init__.py
poetryupvers/data/messages.json
poetryupvers/git.py
poetryupvers/main.py
poetryupvers/release_notes.py
poetryupvers/upvers.py
poetryupvers/util.py
poetryupvers-0.3.4.dist-info/LICENSE
poetryupvers-0.3.4.dist-info/METADATA
poetryupvers-0.3.4.dist-info/WHEEL
poetryupvers-0.3.4.dist-info/entry_points.txt
poetryupvers-0.3.4.dist-info/RECORD
