Metadata-Version: 2.1
Name: PoetryUpvers
Version: 0.3.4
Summary: Semantic versioning on a pyproject.toml
Home-page: https://gitlab.com/gitlab-org/professional-services-automation/tools/utilities/poetryupvers
License: MIT
Author: Michael Leopard
Author-email: mleopard@gitlab.com
Requires-Python: >=3.8.0
Classifier: License :: OSI Approved :: MIT License
Classifier: Programming Language :: Python :: 3
Classifier: Programming Language :: Python :: 3.8
Classifier: Programming Language :: Python :: 3.9
Classifier: Programming Language :: Python :: 3.10
Classifier: Programming Language :: Python :: 3.11
Classifier: Programming Language :: Python :: 3.12
Requires-Dist: docopt (>=0.6.2,<0.7.0)
Requires-Dist: gitlab-ps-utils (>=0.8.0,<0.9.0)
Requires-Dist: semver (>=2.13.0,<3.0.0)
Requires-Dist: tomlkit (>=0.7.2,<0.8.0)
